odoo/addons/account_invoice_mode_at_shipping/README.rst
odoo/addons/account_invoice_mode_at_shipping/__init__.py
odoo/addons/account_invoice_mode_at_shipping/__manifest__.py
odoo/addons/account_invoice_mode_at_shipping/i18n/account_invoice_mode_at_shipping.pot
odoo/addons/account_invoice_mode_at_shipping/models/__init__.py
odoo/addons/account_invoice_mode_at_shipping/models/res_partner.py
odoo/addons/account_invoice_mode_at_shipping/models/stock_move.py
odoo/addons/account_invoice_mode_at_shipping/models/stock_picking.py
odoo/addons/account_invoice_mode_at_shipping/readme/CONTRIBUTORS.rst
odoo/addons/account_invoice_mode_at_shipping/readme/DESCRIPTION.rst
odoo/addons/account_invoice_mode_at_shipping/static/description/icon.png
odoo/addons/account_invoice_mode_at_shipping/static/description/index.html
odoo/addons/account_invoice_mode_at_shipping/tests/__init__.py
odoo/addons/account_invoice_mode_at_shipping/tests/test_invoice_mode_at_shipping.py
odoo13_addon_account_invoice_mode_at_shipping-13.0.1.0.1.dist-info/METADATA
odoo13_addon_account_invoice_mode_at_shipping-13.0.1.0.1.dist-info/WHEEL
odoo13_addon_account_invoice_mode_at_shipping-13.0.1.0.1.dist-info/top_level.txt
odoo13_addon_account_invoice_mode_at_shipping-13.0.1.0.1.dist-info/RECORD
